{
  "title": "关于我们的电影节平台",
  "subtitle": "通过一个无缝、创新的平台，连接全球电影人和电影节组织者。",
  "stats": [
    { "label": "主办的电影节", "value": "10,000+" },
    { "label": "处理的投稿数量", "value": "1M+" },
    { "label": "连接的电影人", "value": "500K+" },
    { "label": "覆盖国家", "value": "150+" }
  ],
  "values": [
    {
      "title": "社区",
      "description": "我们培养一个由全球电影人和电影节组织者组成的社区。"
    },
    {
      "title": "简洁",
      "description": "我们的平台让投稿和管理电影节变得简单直观。"
    },
    {
      "title": "创新",
      "description": "我们利用技术优化电影节的整体体验。"
    },
    {
      "title": "热情",
      "description": "我们致力于通过电影来庆祝讲故事的艺术。"
    }
  ],
  "story": {
    "title": "我们的故事",
    "paragraphs": [
      "我们的平台源于对讲故事的热情和简化电影人与电影节之间联系的愿望。我们起初的愿景是打造一个无缝的全球电影投稿中心。",
      "多年来，我们发展成为全球领先的电影节投稿平台，帮助数千名电影人分享他们的故事，并让电影节发现惊人的人才。",
      "从独立电影人到大型电影节，我们的平台赋予创意和连接力量，让电影节体验变得易于参与且充满回报。"
    ]
  },
  "mission": {
    "title": "我们的使命",
    "description": "通过提供一个用户友好的平台，我们赋能电影人和电影节组织者，简化投稿流程，提升可发现性，并庆祝电影艺术的讲述。",
    "slogan": "连接故事，激发创意"
  }
}
